solaredge/__init__.py
solaredge/api/__init__.py
solaredge/api/client.py
solaredge/api/equipment.py
solaredge/api/error.py
solaredge/api/sites.py
py_solaredge-0.0.4.8.dist-info/LICENSE.txt
py_solaredge-0.0.4.8.dist-info/METADATA
py_solaredge-0.0.4.8.dist-info/WHEEL
py_solaredge-0.0.4.8.dist-info/top_level.txt
py_solaredge-0.0.4.8.dist-info/RECORD
